pycomorb/CharlsonComorbidityIndex.py
pycomorb/CustomComorbidityIndex.py
pycomorb/ElixhauserComorbidityIndex.py
pycomorb/GagneComorbidityIndex.py
pycomorb/HospitalFrailtyRiskScore.py
pycomorb/ICDModifications.py
pycomorb/__init__.py
pycomorb/common/CHARLSON_AUSTRALIA.csv
pycomorb/common/CHARLSON_DEYO.csv
pycomorb/common/CHARLSON_DHOORE.csv
pycomorb/common/CHARLSON_QUAN.csv
pycomorb/common/CHARLSON_RCS.csv
pycomorb/common/CHARLSON_ROMANO.csv
pycomorb/common/CHARLSON_SWEDEN.csv
pycomorb/common/CHARLSON_UK_SHMI_v1.55.csv
pycomorb/common/ELIXHAUSER.csv
pycomorb/common/ELIXHAUSER_AHRQ_ICD10.csv
pycomorb/common/ELIXHAUSER_AHRQ_ICD9.csv
pycomorb/common/ELIXHAUSER_QUAN.csv
pycomorb/common/ELIXHAUSER_WEIGHTS.csv
pycomorb/common/GAGNE.csv
pycomorb/common/HFRS.csv
pycomorb/modification_DE/germanmodification.py
pycomorb/modification_DE/icd10gm.csv
pycomorb/modification_US/clinicalmodification.py
pycomorb/modification_US/icd10cm.csv
pycomorb-0.6.dist-info/licenses/LICENSE
pycomorb-0.6.dist-info/METADATA
pycomorb-0.6.dist-info/WHEEL
pycomorb-0.6.dist-info/top_level.txt
pycomorb-0.6.dist-info/RECORD
