Metadata-Version: 2.4
Name: pycomorb
Version: 0.6
Summary: Comorbidity and frailty score calculation utilities (Charlson, Elixhauser, Gagne, HFRS) using polars
Author-email: Finn Fassbender <finn.fassbender@charite.de>
License-Expression: MIT
Classifier: Programming Language :: Python :: 3
Classifier: Operating System :: OS Independent
Requires-Python: >=3.10
License-File: LICENSE
Requires-Dist: pandas
Requires-Dist: polars>=1.0.0
Dynamic: license-file
